igcoccebot/__init__.py
igcoccebot/coccebot.py
igcoccebot/data.py
igcoccebot/navigation.py
igcoccebot/tools.py
igcoccebot/yolo.py
igcoccebot-0.2.4.dist-info/LICENSE
igcoccebot-0.2.4.dist-info/METADATA
igcoccebot-0.2.4.dist-info/WHEEL
igcoccebot-0.2.4.dist-info/top_level.txt
igcoccebot-0.2.4.dist-info/RECORD
