Metadata-Version: 2.1
Name: igcoccebot
Version: 0.2.4
Summary: The definitive package to interact on Instagram
Home-page: https://github.com/lollococce/igcoccebot
Author: Lorenzo Coacci
Author-email: lorenzo@coacci.com
License: MIT
Keywords: igcoccebot bot instagram selenium AI
Platform: UNKNOWN
Classifier: Programming Language :: Python :: 3
Classifier: License :: OSI Approved :: MIT License
Classifier: Natural Language :: English
Classifier: Topic :: Scientific/Engineering :: Artificial Intelligence
Requires-Dist: selenium
Requires-Dist: pandas
Requires-Dist: datetime
Requires-Dist: termcolor
Requires-Dist: pillow
